{"nodes": [{"id": "src_components_pdf_SurveyReportDocument_tsx", "label": "SurveyReportDocument", "file_type": "code", "source_file": "src\\components\\pdf\\SurveyReportDocument.tsx", "source_location": null, "source_url": null, "captured_at": null, "author": null, "contributor": null}, {"id": "src_components_pdf_UIICReportDocument_tsx", "label": "UIICReportDocument", "file_type": "code", "source_file": "src\\components\\pdf\\UIICReportDocument.tsx", "source_location": null, "source_url": null, "captured_at": null, "author": null, "contributor": null}, {"id": "src_components_print_SpotPrintReport_tsx", "label": "SpotPrintReport", "file_type": "code", "source_file": "src\\components\\print\\SpotPrintReport.tsx", "source_location": null, "source_url": null, "captured_at": null, "author": null, "contributor": null}, {"id": "src_components_print_UIICPrintReport_tsx", "label": "UIICPrintReport", "file_type": "code", "source_file": "src\\components\\print\\UIICPrintReport.tsx", "source_location": null, "source_url": null, "captured_at": null, "author": null, "contributor": null}, {"id": "src_components_tabs_AssessmentTab_tsx", "label": "AssessmentTab", "file_type": "code", "source_file": "src\\components\\tabs\\AssessmentTab.tsx", "source_location": null, "source_url": null, "captured_at": null, "author": null, "contributor": null}, {"id": "src_components_tabs_BillCheckTab_tsx", "label": "BillCheckTab", "file_type": "code", "source_file": "src\\components\\tabs\\BillCheckTab.tsx", "source_location": null, "source_url": null, "captured_at": null, "author": null, "contributor": null}, {"id": "src_components_tabs_CloudVaultTab_tsx", "label": "CloudVaultTab", "file_type": "code", "source_file": "src\\components\\tabs\\CloudVaultTab.tsx", "source_location": null, "source_url": null, "captured_at": null, "author": null, "contributor": null}, {"id": "src_components_tabs_DetailsTab_tsx", "label": "DetailsTab", "file_type": "code", "source_file": "src\\components\\tabs\\DetailsTab.tsx", "source_location": null, "source_url": null, "captured_at": null, "author": null, "contributor": null}, {"id": "src_components_tabs_DocumentsTab_tsx", "label": "DocumentsTab", "file_type": "code", "source_file": "src\\components\\tabs\\DocumentsTab.tsx", "source_location": null, "source_url": null, "captured_at": null, "author": null, "contributor": null}, {"id": "src_components_tabs_FeesTab_tsx", "label": "FeesTab", "file_type": "code", "source_file": "src\\components\\tabs\\FeesTab.tsx", "source_location": null, "source_url": null, "captured_at": null, "author": null, "contributor": null}, {"id": "src_components_tabs_PhotosTab_tsx", "label": "PhotosTab", "file_type": "code", "source_file": "src\\components\\tabs\\PhotosTab.tsx", "source_location": null, "source_url": null, "captured_at": null, "author": null, "contributor": null}, {"id": "src_components_tabs_ProfileTab_tsx", "label": "ProfileTab", "file_type": "code", "source_file": "src\\components\\tabs\\ProfileTab.tsx", "source_location": null, "source_url": null, "captured_at": null, "author": null, "contributor": null}, {"id": "src_components_tabs_ReinspectionTab_tsx", "label": "ReinspectionTab", "file_type": "code", "source_file": "src\\components\\tabs\\ReinspectionTab.tsx", "source_location": null, "source_url": null, "captured_at": null, "author": null, "contributor": null}, {"id": "src_components_tabs_ReportTab_tsx", "label": "ReportTab", "file_type": "code", "source_file": "src\\components\\tabs\\ReportTab.tsx", "source_location": null, "source_url": null, "captured_at": null, "author": null, "contributor": null}, {"id": "src_components_tabs_ReviewTab_tsx", "label": "ReviewTab", "file_type": "code", "source_file": "src\\components\\tabs\\ReviewTab.tsx", "source_location": null, "source_url": null, "captured_at": null, "author": null, "contributor": null}, {"id": "src_components_tabs_SpotTab_tsx", "label": "SpotTab", "file_type": "code", "source_file": "src\\components\\tabs\\SpotTab.tsx", "source_location": null, "source_url": null, "captured_at": null, "author": null, "contributor": null}, {"id": "src_components_tabs_reconciliation_ReconciliationDialog_tsx", "label": "ReconciliationDialog", "file_type": "code", "source_file": "src\\components\\tabs\\reconciliation\\ReconciliationDialog.tsx", "source_location": null, "source_url": null, "captured_at": null, "author": null, "contributor": null}, {"id": "src_components_ui_badge_tsx", "label": "badge", "file_type": "code", "source_file": "src\\components\\ui\\badge.tsx", "source_location": null, "source_url": null, "captured_at": null, "author": null, "contributor": null}, {"id": "src_components_ui_button_tsx", "label": "button", "file_type": "code", "source_file": "src\\components\\ui\\button.tsx", "source_location": null, "source_url": null, "captured_at": null, "author": null, "contributor": null}, {"id": "src_components_ui_card_tsx", "label": "card", "file_type": "code", "source_file": "src\\components\\ui\\card.tsx", "source_location": null, "source_url": null, "captured_at": null, "author": null, "contributor": null}, {"id": "src_components_ui_dialog_tsx", "label": "dialog", "file_type": "code", "source_file": "src\\components\\ui\\dialog.tsx", "source_location": null, "source_url": null, "captured_at": null, "author": null, "contributor": null}, {"id": "src_components_ui_input_tsx", "label": "input", "file_type": "code", "source_file": "src\\components\\ui\\input.tsx", "source_location": null, "source_url": null, "captured_at": null, "author": null, "contributor": null}], "edges": [{"source": "src_components_pdf_SurveyReportDocument_tsx", "target": "src_types'", "relation": "references", "confidence": "EXTRACTED", "confidence_score": 1.0, "source_file": "src\\components\\pdf\\SurveyReportDocument.tsx", "source_location": null, "weight": 1.0}, {"source": "src_components_pdf_UIICReportDocument_tsx", "target": "src_types'", "relation": "references", "confidence": "EXTRACTED", "confidence_score": 1.0, "source_file": "src\\components\\pdf\\UIICReportDocument.tsx", "source_location": null, "weight": 1.0}, {"source": "src_components_print_SpotPrintReport_tsx", "target": "src_types'", "relation": "references", "confidence": "EXTRACTED", "confidence_score": 1.0, "source_file": "src\\components\\print\\SpotPrintReport.tsx", "source_location": null, "weight": 1.0}, {"source": "src_components_print_SpotPrintReport_tsx", "target": "src_lib_calculations'", "relation": "references", "confidence": "EXTRACTED", "confidence_score": 1.0, "source_file": "src\\components\\print\\SpotPrintReport.tsx", "source_location": null, "weight": 1.0}, {"source": "src_components_print_UIICPrintReport_tsx", "target": "src_types'", "relation": "references", "confidence": "EXTRACTED", "confidence_score": 1.0, "source_file": "src\\components\\print\\UIICPrintReport.tsx", "source_location": null, "weight": 1.0}, {"source": "src_components_print_UIICPrintReport_tsx", "target": "src_lib_calculations'", "relation": "references", "confidence": "EXTRACTED", "confidence_score": 1.0, "source_file": "src\\components\\print\\UIICPrintReport.tsx", "source_location": null, "weight": 1.0}, {"source": "src_components_tabs_AssessmentTab_tsx", "target": "src_stores_claim_store'", "relation": "references", "confidence": "EXTRACTED", "confidence_score": 1.0, "source_file": "src\\components\\tabs\\AssessmentTab.tsx", "source_location": null, "weight": 1.0}, {"source": "src_components_tabs_AssessmentTab_tsx", "target": "src_components_claim_AssessmentGrid'", "relation": "references", "confidence": "EXTRACTED", "confidence_score": 1.0, "source_file": "src\\components\\tabs\\AssessmentTab.tsx", "source_location": null, "weight": 1.0}, {"source": "src_components_tabs_AssessmentTab_tsx", "target": "src_components_claim_AssessmentSummary'", "relation": "references", "confidence": "EXTRACTED", "confidence_score": 1.0, "source_file": "src\\components\\tabs\\AssessmentTab.tsx", "source_location": null, "weight": 1.0}, {"source": "src_components_tabs_AssessmentTab_tsx", "target": "src_components_ui_label'", "relation": "references", "confidence": "EXTRACTED", "confidence_score": 1.0, "source_file": "src\\components\\tabs\\AssessmentTab.tsx", "source_location": null, "weight": 1.0}, {"source": "src_components_tabs_BillCheckTab_tsx", "target": "src_stores_claim_store'", "relation": "references", "confidence": "EXTRACTED", "confidence_score": 1.0, "source_file": "src\\components\\tabs\\BillCheckTab.tsx", "source_location": null, "weight": 1.0}, {"source": "src_components_tabs_BillCheckTab_tsx", "target": "src_lib_calculations'", "relation": "references", "confidence": "EXTRACTED", "confidence_score": 1.0, "source_file": "src\\components\\tabs\\BillCheckTab.tsx", "source_location": null, "weight": 1.0}, {"source": "src_components_tabs_BillCheckTab_tsx", "target": "src_lib_reports_uiic_final_builder'", "relation": "references", "confidence": "EXTRACTED", "confidence_score": 1.0, "source_file": "src\\components\\tabs\\BillCheckTab.tsx", "source_location": null, "weight": 1.0}, {"source": "src_components_tabs_BillCheckTab_tsx", "target": "src_stores_profile_store'", "relation": "references", "confidence": "EXTRACTED", "confidence_score": 1.0, "source_file": "src\\components\\tabs\\BillCheckTab.tsx", "source_location": null, "weight": 1.0}, {"source": "src_components_tabs_BillCheckTab_tsx", "target": "src_hooks_useAIExtraction'", "relation": "references", "confidence": "EXTRACTED", "confidence_score": 1.0, "source_file": "src\\components\\tabs\\BillCheckTab.tsx", "source_location": null, "weight": 1.0}, {"source": "src_components_tabs_BillCheckTab_tsx", "target": "src_components_dialogs_AIReviewDialog'", "relation": "references", "confidence": "EXTRACTED", "confidence_score": 1.0, "source_file": "src\\components\\tabs\\BillCheckTab.tsx", "source_location": null, "weight": 1.0}, {"source": "src_components_tabs_CloudVaultTab_tsx", "target": "src_stores_auth_store'", "relation": "references", "confidence": "EXTRACTED", "confidence_score": 1.0, "source_file": "src\\components\\tabs\\CloudVaultTab.tsx", "source_location": null, "weight": 1.0}, {"source": "src_components_tabs_CloudVaultTab_tsx", "target": "src_lib_firebase_sync'", "relation": "references", "confidence": "EXTRACTED", "confidence_score": 1.0, "source_file": "src\\components\\tabs\\CloudVaultTab.tsx", "source_location": null, "weight": 1.0}, {"source": "src_components_tabs_CloudVaultTab_tsx", "target": "src_lib_storage_indexeddb'", "relation": "references", "confidence": "EXTRACTED", "confidence_score": 1.0, "source_file": "src\\components\\tabs\\CloudVaultTab.tsx", "source_location": null, "weight": 1.0}, {"source": "src_components_tabs_CloudVaultTab_tsx", "target": "src_types'", "relation": "references", "confidence": "EXTRACTED", "confidence_score": 1.0, "source_file": "src\\components\\tabs\\CloudVaultTab.tsx", "source_location": null, "weight": 1.0}, {"source": "src_components_tabs_DetailsTab_tsx", "target": "src_components_claim_VehicleForm'", "relation": "references", "confidence": "EXTRACTED", "confidence_score": 1.0, "source_file": "src\\components\\tabs\\DetailsTab.tsx", "source_location": null, "weight": 1.0}, {"source": "src_components_tabs_DetailsTab_tsx", "target": "src_components_claim_DriverForm'", "relation": "references", "confidence": "EXTRACTED", "confidence_score": 1.0, "source_file": "src\\components\\tabs\\DetailsTab.tsx", "source_location": null, "weight": 1.0}, {"source": "src_components_tabs_DetailsTab_tsx", "target": "src_components_claim_PolicyForm'", "relation": "references", "confidence": "EXTRACTED", "confidence_score": 1.0, "source_file": "src\\components\\tabs\\DetailsTab.tsx", "source_location": null, "weight": 1.0}, {"source": "src_components_tabs_DetailsTab_tsx", "target": "src_components_claim_AccidentForm'", "relation": "references", "confidence": "EXTRACTED", "confidence_score": 1.0, "source_file": "src\\components\\tabs\\DetailsTab.tsx", "source_location": null, "weight": 1.0}, {"source": "src_components_tabs_DetailsTab_tsx", "target": "src_hooks_useAIExtraction'", "relation": "references", "confidence": "EXTRACTED", "confidence_score": 1.0, "source_file": "src\\components\\tabs\\DetailsTab.tsx", "source_location": null, "weight": 1.0}, {"source": "src_components_tabs_DetailsTab_tsx", "target": "src_components_dialogs_AIReviewDialog'", "relation": "references", "confidence": "EXTRACTED", "confidence_score": 1.0, "source_file": "src\\components\\tabs\\DetailsTab.tsx", "source_location": null, "weight": 1.0}, {"source": "src_components_tabs_DetailsTab_tsx", "target": "src_stores_claim_store'", "relation": "references", "confidence": "EXTRACTED", "confidence_score": 1.0, "source_file": "src\\components\\tabs\\DetailsTab.tsx", "source_location": null, "weight": 1.0}, {"source": "src_components_tabs_DetailsTab_tsx", "target": "src_lib_reports_word_builder'", "relation": "references", "confidence": "EXTRACTED", "confidence_score": 1.0, "source_file": "src\\components\\tabs\\DetailsTab.tsx", "source_location": null, "weight": 1.0}, {"source": "src_components_tabs_DetailsTab_tsx", "target": "src_components_ui_button'", "relation": "references", "confidence": "EXTRACTED", "confidence_score": 1.0, "source_file": "src\\components\\tabs\\DetailsTab.tsx", "source_location": null, "weight": 1.0}, {"source": "src_components_tabs_DocumentsTab_tsx", "target": "src_hooks_useAIExtraction'", "relation": "references", "confidence": "EXTRACTED", "confidence_score": 1.0, "source_file": "src\\components\\tabs\\DocumentsTab.tsx", "source_location": null, "weight": 1.0}, {"source": "src_components_tabs_DocumentsTab_tsx", "target": "src_components_dialogs_AIReviewDialog'", "relation": "references", "confidence": "EXTRACTED", "confidence_score": 1.0, "source_file": "src\\components\\tabs\\DocumentsTab.tsx", "source_location": null, "weight": 1.0}, {"source": "src_components_tabs_DocumentsTab_tsx", "target": "src_stores_claim_store'", "relation": "references", "confidence": "EXTRACTED", "confidence_score": 1.0, "source_file": "src\\components\\tabs\\DocumentsTab.tsx", "source_location": null, "weight": 1.0}, {"source": "src_components_tabs_DocumentsTab_tsx", "target": "src_lib_drive'", "relation": "references", "confidence": "EXTRACTED", "confidence_score": 1.0, "source_file": "src\\components\\tabs\\DocumentsTab.tsx", "source_location": null, "weight": 1.0}, {"source": "src_components_tabs_DocumentsTab_tsx", "target": "reconciliation_ReconciliationDialog'", "relation": "references", "confidence": "EXTRACTED", "confidence_score": 1.0, "source_file": "src\\components\\tabs\\DocumentsTab.tsx", "source_location": null, "weight": 1.0}, {"source": "src_components_tabs_DocumentsTab_tsx", "target": "src_lib_ai_reconciliation'", "relation": "references", "confidence": "EXTRACTED", "confidence_score": 1.0, "source_file": "src\\components\\tabs\\DocumentsTab.tsx", "source_location": null, "weight": 1.0}, {"source": "src_components_tabs_FeesTab_tsx", "target": "src_stores_claim_store'", "relation": "references", "confidence": "EXTRACTED", "confidence_score": 1.0, "source_file": "src\\components\\tabs\\FeesTab.tsx", "source_location": null, "weight": 1.0}, {"source": "src_components_tabs_FeesTab_tsx", "target": "src_stores_profile_store'", "relation": "references", "confidence": "EXTRACTED", "confidence_score": 1.0, "source_file": "src\\components\\tabs\\FeesTab.tsx", "source_location": null, "weight": 1.0}, {"source": "src_components_tabs_FeesTab_tsx", "target": "src_lib_calculations'", "relation": "references", "confidence": "EXTRACTED", "confidence_score": 1.0, "source_file": "src\\components\\tabs\\FeesTab.tsx", "source_location": null, "weight": 1.0}, {"source": "src_components_tabs_FeesTab_tsx", "target": "src_lib_calculations_depreciation'", "relation": "references", "confidence": "EXTRACTED", "confidence_score": 1.0, "source_file": "src\\components\\tabs\\FeesTab.tsx", "source_location": null, "weight": 1.0}, {"source": "src_components_tabs_FeesTab_tsx", "target": "src_lib_reports_spot_fee_bill_builder'", "relation": "references", "confidence": "EXTRACTED", "confidence_score": 1.0, "source_file": "src\\components\\tabs\\FeesTab.tsx", "source_location": null, "weight": 1.0}, {"source": "src_components_tabs_PhotosTab_tsx", "target": "src_stores_claim_store'", "relation": "references", "confidence": "EXTRACTED", "confidence_score": 1.0, "source_file": "src\\components\\tabs\\PhotosTab.tsx", "source_location": null, "weight": 1.0}, {"source": "src_components_tabs_PhotosTab_tsx", "target": "src_lib_drive'", "relation": "references", "confidence": "EXTRACTED", "confidence_score": 1.0, "source_file": "src\\components\\tabs\\PhotosTab.tsx", "source_location": null, "weight": 1.0}, {"source": "src_components_tabs_PhotosTab_tsx", "target": "src_components_ui_card'", "relation": "references", "confidence": "EXTRACTED", "confidence_score": 1.0, "source_file": "src\\components\\tabs\\PhotosTab.tsx", "source_location": null, "weight": 1.0}, {"source": "src_components_tabs_PhotosTab_tsx", "target": "src_components_ui_input'", "relation": "references", "confidence": "EXTRACTED", "confidence_score": 1.0, "source_file": "src\\components\\tabs\\PhotosTab.tsx", "source_location": null, "weight": 1.0}, {"source": "src_components_tabs_PhotosTab_tsx", "target": "src_components_ui_label'", "relation": "references", "confidence": "EXTRACTED", "confidence_score": 1.0, "source_file": "src\\components\\tabs\\PhotosTab.tsx", "source_location": null, "weight": 1.0}, {"source": "src_components_tabs_PhotosTab_tsx", "target": "src_types'", "relation": "references", "confidence": "EXTRACTED", "confidence_score": 1.0, "source_file": "src\\components\\tabs\\PhotosTab.tsx", "source_location": null, "weight": 1.0}, {"source": "src_components_tabs_ProfileTab_tsx", "target": "src_stores_profile_store'", "relation": "references", "confidence": "EXTRACTED", "confidence_score": 1.0, "source_file": "src\\components\\tabs\\ProfileTab.tsx", "source_location": null, "weight": 1.0}, {"source": "src_components_tabs_ProfileTab_tsx", "target": "src_stores_ui_store'", "relation": "references", "confidence": "EXTRACTED", "confidence_score": 1.0, "source_file": "src\\components\\tabs\\ProfileTab.tsx", "source_location": null, "weight": 1.0}, {"source": "src_components_tabs_ProfileTab_tsx", "target": "src_lib_drive'", "relation": "references", "confidence": "EXTRACTED", "confidence_score": 1.0, "source_file": "src\\components\\tabs\\ProfileTab.tsx", "source_location": null, "weight": 1.0}, {"source": "src_components_tabs_ReinspectionTab_tsx", "target": "src_stores_claim_store'", "relation": "references", "confidence": "EXTRACTED", "confidence_score": 1.0, "source_file": "src\\components\\tabs\\ReinspectionTab.tsx", "source_location": null, "weight": 1.0}, {"source": "src_components_tabs_ReportTab_tsx", "target": "src_stores_claim_store'", "relation": "references", "confidence": "EXTRACTED", "confidence_score": 1.0, "source_file": "src\\components\\tabs\\ReportTab.tsx", "source_location": null, "weight": 1.0}, {"source": "src_components_tabs_ReportTab_tsx", "target": "src_stores_profile_store'", "relation": "references", "confidence": "EXTRACTED", "confidence_score": 1.0, "source_file": "src\\components\\tabs\\ReportTab.tsx", "source_location": null, "weight": 1.0}, {"source": "src_components_tabs_ReportTab_tsx", "target": "src_lib_calculations'", "relation": "references", "confidence": "EXTRACTED", "confidence_score": 1.0, "source_file": "src\\components\\tabs\\ReportTab.tsx", "source_location": null, "weight": 1.0}, {"source": "src_components_tabs_ReportTab_tsx", "target": "src_lib_calculations_depreciation'", "relation": "references", "confidence": "EXTRACTED", "confidence_score": 1.0, "source_file": "src\\components\\tabs\\ReportTab.tsx", "source_location": null, "weight": 1.0}, {"source": "src_components_tabs_ReportTab_tsx", "target": "src_components_ui_card'", "relation": "references", "confidence": "EXTRACTED", "confidence_score": 1.0, "source_file": "src\\components\\tabs\\ReportTab.tsx", "source_location": null, "weight": 1.0}, {"source": "src_components_tabs_ReportTab_tsx", "target": "src_lib_reports_word_builder'", "relation": "references", "confidence": "EXTRACTED", "confidence_score": 1.0, "source_file": "src\\components\\tabs\\ReportTab.tsx", "source_location": null, "weight": 1.0}, {"source": "src_components_tabs_ReportTab_tsx", "target": "src_components_pdf_SurveyReportDocument'", "relation": "references", "confidence": "EXTRACTED", "confidence_score": 1.0, "source_file": "src\\components\\tabs\\ReportTab.tsx", "source_location": null, "weight": 1.0}, {"source": "src_components_tabs_ReportTab_tsx", "target": "src_components_pdf_SpotReportDocument'", "relation": "references", "confidence": "EXTRACTED", "confidence_score": 1.0, "source_file": "src\\components\\tabs\\ReportTab.tsx", "source_location": null, "weight": 1.0}, {"source": "src_components_tabs_ReportTab_tsx", "target": "src_components_pdf_UIICReportDocument'", "relation": "references", "confidence": "EXTRACTED", "confidence_score": 1.0, "source_file": "src\\components\\tabs\\ReportTab.tsx", "source_location": null, "weight": 1.0}, {"source": "src_components_tabs_ReportTab_tsx", "target": "src_components_pdf_BillCheckDocument'", "relation": "references", "confidence": "EXTRACTED", "confidence_score": 1.0, "source_file": "src\\components\\tabs\\ReportTab.tsx", "source_location": null, "weight": 1.0}, {"source": "src_components_tabs_ReportTab_tsx", "target": "src_components_pdf_FeeBillDocument'", "relation": "references", "confidence": "EXTRACTED", "confidence_score": 1.0, "source_file": "src\\components\\tabs\\ReportTab.tsx", "source_location": null, "weight": 1.0}, {"source": "src_components_tabs_ReportTab_tsx", "target": "src_components_print_SpotPrintReport'", "relation": "references", "confidence": "EXTRACTED", "confidence_score": 1.0, "source_file": "src\\components\\tabs\\ReportTab.tsx", "source_location": null, "weight": 1.0}, {"source": "src_components_tabs_ReportTab_tsx", "target": "src_components_print_UIICPrintReport'", "relation": "references", "confidence": "EXTRACTED", "confidence_score": 1.0, "source_file": "src\\components\\tabs\\ReportTab.tsx", "source_location": null, "weight": 1.0}, {"source": "src_components_tabs_ReportTab_tsx", "target": "src_lib_reports_standard_report_builder'", "relation": "references", "confidence": "EXTRACTED", "confidence_score": 1.0, "source_file": "src\\components\\tabs\\ReportTab.tsx", "source_location": null, "weight": 1.0}, {"source": "src_components_tabs_ReportTab_tsx", "target": "src_lib_reports_spot_fee_bill_builder'", "relation": "references", "confidence": "EXTRACTED", "confidence_score": 1.0, "source_file": "src\\components\\tabs\\ReportTab.tsx", "source_location": null, "weight": 1.0}, {"source": "src_components_tabs_ReportTab_tsx", "target": "src_lib_reports_uiic_final_builder'", "relation": "references", "confidence": "EXTRACTED", "confidence_score": 1.0, "source_file": "src\\components\\tabs\\ReportTab.tsx", "source_location": null, "weight": 1.0}, {"source": "src_components_tabs_ReviewTab_tsx", "target": "src_stores_claim_store'", "relation": "references", "confidence": "EXTRACTED", "confidence_score": 1.0, "source_file": "src\\components\\tabs\\ReviewTab.tsx", "source_location": null, "weight": 1.0}, {"source": "src_components_tabs_ReviewTab_tsx", "target": "src_stores_ui_store'", "relation": "references", "confidence": "EXTRACTED", "confidence_score": 1.0, "source_file": "src\\components\\tabs\\ReviewTab.tsx", "source_location": null, "weight": 1.0}, {"source": "src_components_tabs_SpotTab_tsx", "target": "src_stores_claim_store'", "relation": "references", "confidence": "EXTRACTED", "confidence_score": 1.0, "source_file": "src\\components\\tabs\\SpotTab.tsx", "source_location": null, "weight": 1.0}, {"source": "src_components_tabs_SpotTab_tsx", "target": "src_stores_profile_store'", "relation": "references", "confidence": "EXTRACTED", "confidence_score": 1.0, "source_file": "src\\components\\tabs\\SpotTab.tsx", "source_location": null, "weight": 1.0}, {"source": "src_components_tabs_SpotTab_tsx", "target": "src_components_ui_card'", "relation": "references", "confidence": "EXTRACTED", "confidence_score": 1.0, "source_file": "src\\components\\tabs\\SpotTab.tsx", "source_location": null, "weight": 1.0}, {"source": "src_components_tabs_SpotTab_tsx", "target": "src_components_ui_input'", "relation": "references", "confidence": "EXTRACTED", "confidence_score": 1.0, "source_file": "src\\components\\tabs\\SpotTab.tsx", "source_location": null, "weight": 1.0}, {"source": "src_components_tabs_SpotTab_tsx", "target": "src_components_ui_label'", "relation": "references", "confidence": "EXTRACTED", "confidence_score": 1.0, "source_file": "src\\components\\tabs\\SpotTab.tsx", "source_location": null, "weight": 1.0}, {"source": "src_components_tabs_reconciliation_ReconciliationDialog_tsx", "target": "src_components_ui_card'", "relation": "references", "confidence": "EXTRACTED", "confidence_score": 1.0, "source_file": "src\\components\\tabs\\reconciliation\\ReconciliationDialog.tsx", "source_location": null, "weight": 1.0}, {"source": "src_components_tabs_reconciliation_ReconciliationDialog_tsx", "target": "src_stores_claim_store'", "relation": "references", "confidence": "EXTRACTED", "confidence_score": 1.0, "source_file": "src\\components\\tabs\\reconciliation\\ReconciliationDialog.tsx", "source_location": null, "weight": 1.0}, {"source": "src_components_tabs_reconciliation_ReconciliationDialog_tsx", "target": "src_lib_ai_reconciliation'", "relation": "references", "confidence": "EXTRACTED", "confidence_score": 1.0, "source_file": "src\\components\\tabs\\reconciliation\\ReconciliationDialog.tsx", "source_location": null, "weight": 1.0}, {"source": "src_components_ui_badge_tsx", "target": "src_lib_utils", "relation": "references", "confidence": "EXTRACTED", "confidence_score": 1.0, "source_file": "src\\components\\ui\\badge.tsx", "source_location": null, "weight": 1.0}, {"source": "src_components_ui_button_tsx", "target": "src_lib_utils", "relation": "references", "confidence": "EXTRACTED", "confidence_score": 1.0, "source_file": "src\\components\\ui\\button.tsx", "source_location": null, "weight": 1.0}, {"source": "src_components_ui_card_tsx", "target": "src_lib_utils", "relation": "references", "confidence": "EXTRACTED", "confidence_score": 1.0, "source_file": "src\\components\\ui\\card.tsx", "source_location": null, "weight": 1.0}, {"source": "src_components_ui_dialog_tsx", "target": "src_lib_utils", "relation": "references", "confidence": "EXTRACTED", "confidence_score": 1.0, "source_file": "src\\components\\ui\\dialog.tsx", "source_location": null, "weight": 1.0}, {"source": "src_components_ui_dialog_tsx", "target": "src_components_ui_button", "relation": "references", "confidence": "EXTRACTED", "confidence_score": 1.0, "source_file": "src\\components\\ui\\dialog.tsx", "source_location": null, "weight": 1.0}, {"source": "src_components_ui_input_tsx", "target": "src_lib_utils", "relation": "references", "confidence": "EXTRACTED", "confidence_score": 1.0, "source_file": "src\\components\\ui\\input.tsx", "source_location": null, "weight": 1.0}], "hyperedges": [], "input_tokens": 0, "output_tokens": 0}