{"nodes": [{"id": "getdefaultoptions", "label": "getDefaultOptions.js", "file_type": "code", "source_file": "node_modules\\date-fns\\getDefaultOptions.js", "source_location": "L1"}, {"id": "getdefaultoptions_getdefaultoptions", "label": "getDefaultOptions()", "file_type": "code", "source_file": "node_modules\\date-fns\\getDefaultOptions.js", "source_location": "L27"}], "edges": [{"source": "getdefaultoptions", "target": "defaultoptions_js", "relation": "imports_from", "confidence": "EXTRACTED", "source_file": "node_modules\\date-fns\\getDefaultOptions.js", "source_location": "L1", "weight": 1.0}, {"source": "getdefaultoptions", "target": "getdefaultoptions_getdefaultoptions", "relation": "contains", "confidence": "EXTRACTED", "source_file": "node_modules\\date-fns\\getDefaultOptions.js", "source_location": "L27", "weight": 1.0}]}