{"nodes": [{"id": "isencrypted", "label": "isEncrypted.js", "file_type": "code", "source_file": "node_modules\\@dotenvx\\dotenvx\\src\\lib\\helpers\\cryptography\\isEncrypted.js", "source_location": "L1"}, {"id": "isencrypted_isencrypted", "label": "isEncrypted()", "file_type": "code", "source_file": "node_modules\\@dotenvx\\dotenvx\\src\\lib\\helpers\\cryptography\\isEncrypted.js", "source_location": "L3"}], "edges": [{"source": "isencrypted", "target": "isencrypted_isencrypted", "relation": "contains", "confidence": "EXTRACTED", "source_file": "node_modules\\@dotenvx\\dotenvx\\src\\lib\\helpers\\cryptography\\isEncrypted.js", "source_location": "L3", "weight": 1.0}]}