{"nodes": [{"id": "hydration_error_state", "label": "hydration-error-state.js", "file_type": "code", "source_file": "node_modules\\next\\dist\\next-devtools\\userspace\\pages\\hydration-error-state.js", "source_location": "L1"}, {"id": "hydration_error_state_export", "label": "_export()", "file_type": "code", "source_file": "node_modules\\next\\dist\\next-devtools\\userspace\\pages\\hydration-error-state.js", "source_location": "L10"}, {"id": "hydration_error_state_getsquashedhydrationerrordetails", "label": "getSquashedHydrationErrorDetails()", "file_type": "code", "source_file": "node_modules\\next\\dist\\next-devtools\\userspace\\pages\\hydration-error-state.js", "source_location": "L34"}, {"id": "hydration_error_state_attachhydrationerrorstate", "label": "attachHydrationErrorState()", "file_type": "code", "source_file": "node_modules\\next\\dist\\next-devtools\\userspace\\pages\\hydration-error-state.js", "source_location": "L37"}, {"id": "hydration_error_state_storehydrationerrorstatefromconsoleargs", "label": "storeHydrationErrorStateFromConsoleArgs()", "file_type": "code", "source_file": "node_modules\\next\\dist\\next-devtools\\userspace\\pages\\hydration-error-state.js", "source_location": "L60"}, {"id": "hydration_error_state_generatehydrationdiffreact18", "label": "generateHydrationDiffReact18()", "file_type": "code", "source_file": "node_modules\\next\\dist\\next-devtools\\userspace\\pages\\hydration-error-state.js", "source_location": "L107"}], "edges": [{"source": "hydration_error_state", "target": "hydration_error_state_export", "relation": "contains", "confidence": "EXTRACTED", "source_file": "node_modules\\next\\dist\\next-devtools\\userspace\\pages\\hydration-error-state.js", "source_location": "L10", "weight": 1.0}, {"source": "hydration_error_state", "target": "hydration_error_state_getsquashedhydrationerrordetails", "relation": "contains", "confidence": "EXTRACTED", "source_file": "node_modules\\next\\dist\\next-devtools\\userspace\\pages\\hydration-error-state.js", "source_location": "L34", "weight": 1.0}, {"source": "hydration_error_state", "target": "hydration_error_state_attachhydrationerrorstate", "relation": "contains", "confidence": "EXTRACTED", "source_file": "node_modules\\next\\dist\\next-devtools\\userspace\\pages\\hydration-error-state.js", "source_location": "L37", "weight": 1.0}, {"source": "hydration_error_state", "target": "hydration_error_state_storehydrationerrorstatefromconsoleargs", "relation": "contains", "confidence": "EXTRACTED", "source_file": "node_modules\\next\\dist\\next-devtools\\userspace\\pages\\hydration-error-state.js", "source_location": "L60", "weight": 1.0}, {"source": "hydration_error_state", "target": "hydration_error_state_generatehydrationdiffreact18", "relation": "contains", "confidence": "EXTRACTED", "source_file": "node_modules\\next\\dist\\next-devtools\\userspace\\pages\\hydration-error-state.js", "source_location": "L107", "weight": 1.0}, {"source": "hydration_error_state_storehydrationerrorstatefromconsoleargs", "target": "hydration_error_state_generatehydrationdiffreact18", "relation": "calls", "confidence": "EXTRACTED", "source_file": "node_modules\\next\\dist\\next-devtools\\userspace\\pages\\hydration-error-state.js", "source_location": "L73", "weight": 1.0}]}