{"nodes": [{"id": "useregisteredlabelid", "label": "useRegisteredLabelId.js", "file_type": "code", "source_file": "node_modules\\@base-ui\\react\\utils\\useRegisteredLabelId.js", "source_location": "L1"}, {"id": "useregisteredlabelid_useregisteredlabelid", "label": "useRegisteredLabelId()", "file_type": "code", "source_file": "node_modules\\@base-ui\\react\\utils\\useRegisteredLabelId.js", "source_location": "L10"}], "edges": [{"source": "useregisteredlabelid", "target": "useregisteredlabelid_useregisteredlabelid", "relation": "contains", "confidence": "EXTRACTED", "source_file": "node_modules\\@base-ui\\react\\utils\\useRegisteredLabelId.js", "source_location": "L10", "weight": 1.0}]}