{"nodes": [{"id": "scrollarearoot", "label": "ScrollAreaRoot.js", "file_type": "code", "source_file": "node_modules\\@base-ui\\react\\scroll-area\\root\\ScrollAreaRoot.js", "source_location": "L1"}, {"id": "scrollarearoot_normalizeoverflowedgethreshold", "label": "normalizeOverflowEdgeThreshold()", "file_type": "code", "source_file": "node_modules\\@base-ui\\react\\scroll-area\\root\\ScrollAreaRoot.js", "source_location": "L250"}], "edges": [{"source": "scrollarearoot", "target": "scrollarearoot_normalizeoverflowedgethreshold", "relation": "contains", "confidence": "EXTRACTED", "source_file": "node_modules\\@base-ui\\react\\scroll-area\\root\\ScrollAreaRoot.js", "source_location": "L250", "weight": 1.0}]}