{"nodes": [{"id": "form_shared", "label": "form-shared.js", "file_type": "code", "source_file": "node_modules\\next\\dist\\esm\\client\\form-shared.js", "source_location": "L1"}, {"id": "form_shared_createformsubmitdestinationurl", "label": "createFormSubmitDestinationUrl()", "file_type": "code", "source_file": "node_modules\\next\\dist\\esm\\client\\form-shared.js", "source_location": "L6"}, {"id": "form_shared_checkformactionurl", "label": "checkFormActionUrl()", "file_type": "code", "source_file": "node_modules\\next\\dist\\esm\\client\\form-shared.js", "source_location": "L52"}, {"id": "form_shared_issupportedformenctype", "label": "isSupportedFormEncType()", "file_type": "code", "source_file": "node_modules\\next\\dist\\esm\\client\\form-shared.js", "source_location": "L66"}, {"id": "form_shared_issupportedformmethod", "label": "isSupportedFormMethod()", "file_type": "code", "source_file": "node_modules\\next\\dist\\esm\\client\\form-shared.js", "source_location": "L67"}, {"id": "form_shared_issupportedformtarget", "label": "isSupportedFormTarget()", "file_type": "code", "source_file": "node_modules\\next\\dist\\esm\\client\\form-shared.js", "source_location": "L68"}, {"id": "form_shared_hasunsupportedsubmitterattributes", "label": "hasUnsupportedSubmitterAttributes()", "file_type": "code", "source_file": "node_modules\\next\\dist\\esm\\client\\form-shared.js", "source_location": "L69"}, {"id": "form_shared_hasreactclientactionattributes", "label": "hasReactClientActionAttributes()", "file_type": "code", "source_file": "node_modules\\next\\dist\\esm\\client\\form-shared.js", "source_location": "L96"}], "edges": [{"source": "form_shared", "target": "form_shared_createformsubmitdestinationurl", "relation": "contains", "confidence": "EXTRACTED", "source_file": "node_modules\\next\\dist\\esm\\client\\form-shared.js", "source_location": "L6", "weight": 1.0}, {"source": "form_shared", "target": "form_shared_checkformactionurl", "relation": "contains", "confidence": "EXTRACTED", "source_file": "node_modules\\next\\dist\\esm\\client\\form-shared.js", "source_location": "L52", "weight": 1.0}, {"source": "form_shared", "target": "form_shared_issupportedformenctype", "relation": "contains", "confidence": "EXTRACTED", "source_file": "node_modules\\next\\dist\\esm\\client\\form-shared.js", "source_location": "L66", "weight": 1.0}, {"source": "form_shared", "target": "form_shared_issupportedformmethod", "relation": "contains", "confidence": "EXTRACTED", "source_file": "node_modules\\next\\dist\\esm\\client\\form-shared.js", "source_location": "L67", "weight": 1.0}, {"source": "form_shared", "target": "form_shared_issupportedformtarget", "relation": "contains", "confidence": "EXTRACTED", "source_file": "node_modules\\next\\dist\\esm\\client\\form-shared.js", "source_location": "L68", "weight": 1.0}, {"source": "form_shared", "target": "form_shared_hasunsupportedsubmitterattributes", "relation": "contains", "confidence": "EXTRACTED", "source_file": "node_modules\\next\\dist\\esm\\client\\form-shared.js", "source_location": "L69", "weight": 1.0}, {"source": "form_shared", "target": "form_shared_hasreactclientactionattributes", "relation": "contains", "confidence": "EXTRACTED", "source_file": "node_modules\\next\\dist\\esm\\client\\form-shared.js", "source_location": "L96", "weight": 1.0}, {"source": "form_shared_hasunsupportedsubmitterattributes", "target": "form_shared_issupportedformenctype", "relation": "calls", "confidence": "EXTRACTED", "source_file": "node_modules\\next\\dist\\esm\\client\\form-shared.js", "source_location": "L72", "weight": 1.0}, {"source": "form_shared_hasunsupportedsubmitterattributes", "target": "form_shared_issupportedformmethod", "relation": "calls", "confidence": "EXTRACTED", "source_file": "node_modules\\next\\dist\\esm\\client\\form-shared.js", "source_location": "L80", "weight": 1.0}, {"source": "form_shared_hasunsupportedsubmitterattributes", "target": "form_shared_issupportedformtarget", "relation": "calls", "confidence": "EXTRACTED", "source_file": "node_modules\\next\\dist\\esm\\client\\form-shared.js", "source_location": "L88", "weight": 1.0}]}