{"nodes": [{"id": "index", "label": "index.ts", "file_type": "code", "source_file": "node_modules\\rettime\\src\\index.ts", "source_location": "L1"}, {"id": "index_typedevent", "label": "TypedEvent", "file_type": "code", "source_file": "node_modules\\rettime\\src\\index.ts", "source_location": "L30"}, {"id": "index_typedevent_constructor", "label": ".constructor()", "file_type": "code", "source_file": "node_modules\\rettime\\src\\index.ts", "source_location": "L49"}, {"id": "index_typedevent_defaultprevented", "label": ".defaultPrevented()", "file_type": "code", "source_file": "node_modules\\rettime\\src\\index.ts", "source_location": "L58"}, {"id": "index_typedevent_preventdefault", "label": ".preventDefault()", "file_type": "code", "source_file": "node_modules\\rettime\\src\\index.ts", "source_location": "L62"}, {"id": "index_typedevent_stopimmediatepropagation", "label": ".stopImmediatePropagation()", "file_type": "code", "source_file": "node_modules\\rettime\\src\\index.ts", "source_location": "L67"}, {"id": "index_emitter", "label": "Emitter", "file_type": "code", "source_file": "node_modules\\rettime\\src\\index.ts", "source_location": "L195"}, {"id": "index_emitter_constructor", "label": ".constructor()", "file_type": "code", "source_file": "node_modules\\rettime\\src\\index.ts", "source_location": "L204"}, {"id": "index_emitter_on", "label": ".on()", "file_type": "code", "source_file": "node_modules\\rettime\\src\\index.ts", "source_location": "L211"}, {"id": "index_emitter_once", "label": ".once()", "file_type": "code", "source_file": "node_modules\\rettime\\src\\index.ts", "source_location": "L227"}, {"id": "index_emitter_earlyon", "label": ".earlyOn()", "file_type": "code", "source_file": "node_modules\\rettime\\src\\index.ts", "source_location": "L245"}, {"id": "index_emitter_earlyonce", "label": ".earlyOnce()", "file_type": "code", "source_file": "node_modules\\rettime\\src\\index.ts", "source_location": "L261"}, {"id": "index_emitter_emit", "label": ".emit()", "file_type": "code", "source_file": "node_modules\\rettime\\src\\index.ts", "source_location": "L281"}, {"id": "index_emitter_emitaspromise", "label": ".emitAsPromise()", "file_type": "code", "source_file": "node_modules\\rettime\\src\\index.ts", "source_location": "L324"}, {"id": "index_emitter_emitasgenerator", "label": ".emitAsGenerator()", "file_type": "code", "source_file": "node_modules\\rettime\\src\\index.ts", "source_location": "L377"}, {"id": "index_emitter_removelistener", "label": ".removeListener()", "file_type": "code", "source_file": "node_modules\\rettime\\src\\index.ts", "source_location": "L412"}, {"id": "index_emitter_removealllisteners", "label": ".removeAllListeners()", "file_type": "code", "source_file": "node_modules\\rettime\\src\\index.ts", "source_location": "L429"}, {"id": "index_emitter_listeners", "label": ".listeners()", "file_type": "code", "source_file": "node_modules\\rettime\\src\\index.ts", "source_location": "L444"}, {"id": "index_emitter_listenercount", "label": ".listenerCount()", "file_type": "code", "source_file": "node_modules\\rettime\\src\\index.ts", "source_location": "L460"}, {"id": "index_emitter_addlistener", "label": ".#addListener()", "file_type": "code", "source_file": "node_modules\\rettime\\src\\index.ts", "source_location": "L470"}, {"id": "index_emitter_proxyevent", "label": ".#proxyEvent()", "file_type": "code", "source_file": "node_modules\\rettime\\src\\index.ts", "source_location": "L505"}, {"id": "index_emitter_calllistener", "label": ".#callListener()", "file_type": "code", "source_file": "node_modules\\rettime\\src\\index.ts", "source_location": "L525"}, {"id": "index_emitter_matchlisteners", "label": ".#matchListeners()", "file_type": "code", "source_file": "node_modules\\rettime\\src\\index.ts", "source_location": "L545"}, {"id": "index_emitter_istypelesslistener", "label": ".#isTypelessListener()", "file_type": "code", "source_file": "node_modules\\rettime\\src\\index.ts", "source_location": "L553"}], "edges": [{"source": "index", "target": "lens_list", "relation": "imports_from", "confidence": "EXTRACTED", "source_file": "node_modules\\rettime\\src\\index.ts", "source_location": "L1", "weight": 1.0}, {"source": "index", "target": "index_typedevent", "relation": "contains", "confidence": "EXTRACTED", "source_file": "node_modules\\rettime\\src\\index.ts", "source_location": "L30", "weight": 1.0}, {"source": "index_typedevent", "target": "index_typedevent_constructor", "relation": "method", "confidence": "EXTRACTED", "source_file": "node_modules\\rettime\\src\\index.ts", "source_location": "L49", "weight": 1.0}, {"source": "index_typedevent", "target": "index_typedevent_defaultprevented", "relation": "method", "confidence": "EXTRACTED", "source_file": "node_modules\\rettime\\src\\index.ts", "source_location": "L58", "weight": 1.0}, {"source": "index_typedevent", "target": "index_typedevent_preventdefault", "relation": "method", "confidence": "EXTRACTED", "source_file": "node_modules\\rettime\\src\\index.ts", "source_location": "L62", "weight": 1.0}, {"source": "index_typedevent", "target": "index_typedevent_stopimmediatepropagation", "relation": "method", "confidence": "EXTRACTED", "source_file": "node_modules\\rettime\\src\\index.ts", "source_location": "L67", "weight": 1.0}, {"source": "index", "target": "index_emitter", "relation": "contains", "confidence": "EXTRACTED", "source_file": "node_modules\\rettime\\src\\index.ts", "source_location": "L195", "weight": 1.0}, {"source": "index_emitter", "target": "index_emitter_constructor", "relation": "method", "confidence": "EXTRACTED", "source_file": "node_modules\\rettime\\src\\index.ts", "source_location": "L204", "weight": 1.0}, {"source": "index_emitter", "target": "index_emitter_on", "relation": "method", "confidence": "EXTRACTED", "source_file": "node_modules\\rettime\\src\\index.ts", "source_location": "L211", "weight": 1.0}, {"source": "index_emitter", "target": "index_emitter_once", "relation": "method", "confidence": "EXTRACTED", "source_file": "node_modules\\rettime\\src\\index.ts", "source_location": "L227", "weight": 1.0}, {"source": "index_emitter", "target": "index_emitter_earlyon", "relation": "method", "confidence": "EXTRACTED", "source_file": "node_modules\\rettime\\src\\index.ts", "source_location": "L245", "weight": 1.0}, {"source": "index_emitter", "target": "index_emitter_earlyonce", "relation": "method", "confidence": "EXTRACTED", "source_file": "node_modules\\rettime\\src\\index.ts", "source_location": "L261", "weight": 1.0}, {"source": "index_emitter", "target": "index_emitter_emit", "relation": "method", "confidence": "EXTRACTED", "source_file": "node_modules\\rettime\\src\\index.ts", "source_location": "L281", "weight": 1.0}, {"source": "index_emitter", "target": "index_emitter_emitaspromise", "relation": "method", "confidence": "EXTRACTED", "source_file": "node_modules\\rettime\\src\\index.ts", "source_location": "L324", "weight": 1.0}, {"source": "index_emitter", "target": "index_emitter_emitasgenerator", "relation": "method", "confidence": "EXTRACTED", "source_file": "node_modules\\rettime\\src\\index.ts", "source_location": "L377", "weight": 1.0}, {"source": "index_emitter", "target": "index_emitter_removelistener", "relation": "method", "confidence": "EXTRACTED", "source_file": "node_modules\\rettime\\src\\index.ts", "source_location": "L412", "weight": 1.0}, {"source": "index_emitter", "target": "index_emitter_removealllisteners", "relation": "method", "confidence": "EXTRACTED", "source_file": "node_modules\\rettime\\src\\index.ts", "source_location": "L429", "weight": 1.0}, {"source": "index_emitter", "target": "index_emitter_listeners", "relation": "method", "confidence": "EXTRACTED", "source_file": "node_modules\\rettime\\src\\index.ts", "source_location": "L444", "weight": 1.0}, {"source": "index_emitter", "target": "index_emitter_listenercount", "relation": "method", "confidence": "EXTRACTED", "source_file": "node_modules\\rettime\\src\\index.ts", "source_location": "L460", "weight": 1.0}, {"source": "index_emitter", "target": "index_emitter_addlistener", "relation": "method", "confidence": "EXTRACTED", "source_file": "node_modules\\rettime\\src\\index.ts", "source_location": "L470", "weight": 1.0}, {"source": "index_emitter", "target": "index_emitter_proxyevent", "relation": "method", "confidence": "EXTRACTED", "source_file": "node_modules\\rettime\\src\\index.ts", "source_location": "L505", "weight": 1.0}, {"source": "index_emitter", "target": "index_emitter_calllistener", "relation": "method", "confidence": "EXTRACTED", "source_file": "node_modules\\rettime\\src\\index.ts", "source_location": "L525", "weight": 1.0}, {"source": "index_emitter", "target": "index_emitter_matchlisteners", "relation": "method", "confidence": "EXTRACTED", "source_file": "node_modules\\rettime\\src\\index.ts", "source_location": "L545", "weight": 1.0}, {"source": "index_emitter", "target": "index_emitter_istypelesslistener", "relation": "method", "confidence": "EXTRACTED", "source_file": "node_modules\\rettime\\src\\index.ts", "source_location": "L553", "weight": 1.0}, {"source": "index_emitter_on", "target": "index_emitter_addlistener", "relation": "calls", "confidence": "EXTRACTED", "source_file": "node_modules\\rettime\\src\\index.ts", "source_location": "L220", "weight": 1.0}, {"source": "index_emitter_once", "target": "index_emitter_on", "relation": "calls", "confidence": "EXTRACTED", "source_file": "node_modules\\rettime\\src\\index.ts", "source_location": "L236", "weight": 1.0}, {"source": "index_emitter_earlyon", "target": "index_emitter_addlistener", "relation": "calls", "confidence": "EXTRACTED", "source_file": "node_modules\\rettime\\src\\index.ts", "source_location": "L254", "weight": 1.0}, {"source": "index_emitter_earlyonce", "target": "index_emitter_earlyon", "relation": "calls", "confidence": "EXTRACTED", "source_file": "node_modules\\rettime\\src\\index.ts", "source_location": "L270", "weight": 1.0}, {"source": "index_emitter_emit", "target": "index_emitter_listenercount", "relation": "calls", "confidence": "EXTRACTED", "source_file": "node_modules\\rettime\\src\\index.ts", "source_location": "L292", "weight": 1.0}, {"source": "index_emitter_emit", "target": "index_emitter_proxyevent", "relation": "calls", "confidence": "EXTRACTED", "source_file": "node_modules\\rettime\\src\\index.ts", "source_location": "L294", "weight": 1.0}, {"source": "index_emitter_emit", "target": "index_emitter_matchlisteners", "relation": "calls", "confidence": "EXTRACTED", "source_file": "node_modules\\rettime\\src\\index.ts", "source_location": "L296", "weight": 1.0}, {"source": "index_emitter_emit", "target": "index_emitter_calllistener", "relation": "calls", "confidence": "EXTRACTED", "source_file": "node_modules\\rettime\\src\\index.ts", "source_location": "L309", "weight": 1.0}, {"source": "index_emitter_emitaspromise", "target": "index_emitter_proxyevent", "relation": "calls", "confidence": "EXTRACTED", "source_file": "node_modules\\rettime\\src\\index.ts", "source_location": "L337", "weight": 1.0}, {"source": "index_emitter_emitaspromise", "target": "index_emitter_matchlisteners", "relation": "calls", "confidence": "EXTRACTED", "source_file": "node_modules\\rettime\\src\\index.ts", "source_location": "L339", "weight": 1.0}, {"source": "index_emitter_emitaspromise", "target": "index_emitter_calllistener", "relation": "calls", "confidence": "EXTRACTED", "source_file": "node_modules\\rettime\\src\\index.ts", "source_location": "L353", "weight": 1.0}, {"source": "index_emitter_emitaspromise", "target": "index_emitter_istypelesslistener", "relation": "calls", "confidence": "EXTRACTED", "source_file": "node_modules\\rettime\\src\\index.ts", "source_location": "L358", "weight": 1.0}, {"source": "index_emitter_emitasgenerator", "target": "index_emitter_proxyevent", "relation": "calls", "confidence": "EXTRACTED", "source_file": "node_modules\\rettime\\src\\index.ts", "source_location": "L384", "weight": 1.0}, {"source": "index_emitter_emitasgenerator", "target": "index_emitter_matchlisteners", "relation": "calls", "confidence": "EXTRACTED", "source_file": "node_modules\\rettime\\src\\index.ts", "source_location": "L386", "weight": 1.0}, {"source": "index_emitter_emitasgenerator", "target": "index_emitter_calllistener", "relation": "calls", "confidence": "EXTRACTED", "source_file": "node_modules\\rettime\\src\\index.ts", "source_location": "L399", "weight": 1.0}, {"source": "index_emitter_emitasgenerator", "target": "index_emitter_istypelesslistener", "relation": "calls", "confidence": "EXTRACTED", "source_file": "node_modules\\rettime\\src\\index.ts", "source_location": "L401", "weight": 1.0}, {"source": "index_emitter_listenercount", "target": "index_emitter_listeners", "relation": "calls", "confidence": "EXTRACTED", "source_file": "node_modules\\rettime\\src\\index.ts", "source_location": "L467", "weight": 1.0}, {"source": "index_emitter_calllistener", "target": "index_emitter_istypelesslistener", "relation": "calls", "confidence": "EXTRACTED", "source_file": "node_modules\\rettime\\src\\index.ts", "source_location": "L534", "weight": 1.0}]}