{"nodes": [{"id": "selectpopup", "label": "SelectPopup.js", "file_type": "code", "source_file": "node_modules\\@base-ui\\react\\select\\popup\\SelectPopup.js", "source_location": "L1"}, {"id": "selectpopup_getmaxpopupheight", "label": "getMaxPopupHeight()", "file_type": "code", "source_file": "node_modules\\@base-ui\\react\\select\\popup\\SelectPopup.js", "source_location": "L426"}, {"id": "selectpopup_getmaxscrolltop", "label": "getMaxScrollTop()", "file_type": "code", "source_file": "node_modules\\@base-ui\\react\\select\\popup\\SelectPopup.js", "source_location": "L430"}, {"id": "selectpopup_getscale", "label": "getScale()", "file_type": "code", "source_file": "node_modules\\@base-ui\\react\\select\\popup\\SelectPopup.js", "source_location": "L433"}, {"id": "selectpopup_normalizerect", "label": "normalizeRect()", "file_type": "code", "source_file": "node_modules\\@base-ui\\react\\select\\popup\\SelectPopup.js", "source_location": "L437"}, {"id": "selectpopup_unsettransformstyles", "label": "unsetTransformStyles()", "file_type": "code", "source_file": "node_modules\\@base-ui\\react\\select\\popup\\SelectPopup.js", "source_location": "L446"}], "edges": [{"source": "selectpopup", "target": "selectpopup_getmaxpopupheight", "relation": "contains", "confidence": "EXTRACTED", "source_file": "node_modules\\@base-ui\\react\\select\\popup\\SelectPopup.js", "source_location": "L426", "weight": 1.0}, {"source": "selectpopup", "target": "selectpopup_getmaxscrolltop", "relation": "contains", "confidence": "EXTRACTED", "source_file": "node_modules\\@base-ui\\react\\select\\popup\\SelectPopup.js", "source_location": "L430", "weight": 1.0}, {"source": "selectpopup", "target": "selectpopup_getscale", "relation": "contains", "confidence": "EXTRACTED", "source_file": "node_modules\\@base-ui\\react\\select\\popup\\SelectPopup.js", "source_location": "L433", "weight": 1.0}, {"source": "selectpopup", "target": "selectpopup_normalizerect", "relation": "contains", "confidence": "EXTRACTED", "source_file": "node_modules\\@base-ui\\react\\select\\popup\\SelectPopup.js", "source_location": "L437", "weight": 1.0}, {"source": "selectpopup", "target": "selectpopup_unsettransformstyles", "relation": "contains", "confidence": "EXTRACTED", "source_file": "node_modules\\@base-ui\\react\\select\\popup\\SelectPopup.js", "source_location": "L446", "weight": 1.0}]}